{"container_type": "Author", "filled": ["basics", "publications", "indices", "counts"], "scholar_id": "BBwRN1wAAAAJ&hl=zh-CN", "source": "AUTHOR_PROFILE_PAGE", "name": "Linjie Huang", "url_picture": "https://scholar.googleusercontent.com/citations?view_op=view_photo&user=BBwRN1wAAAAJ&citpid=1", "affiliation": "Ph.D. student, Guangzhou University", "interests": ["Surface damage detection"], "email_domain": "@-", "homepage": "https://gzhu-shm.github.io/hlj.github.io/", "citedby": 63, "publications": {"BBwRN1wAAAAJ:u-x6o8ySG0sC": {"container_type": "Publication", "source": "AUTHOR_PUBLICATION_ENTRY", "bib": {"title": "Deep learning for automated multiclass surface damage detection in bridge inspections", "pub_year": "2024"}, "filled": false, "author_pub_id": "BBwRN1wAAAAJ:u-x6o8ySG0sC", "num_citations": 54, "citedby_url": "https://scholar.google.com/scholar?oi=bibs&hl=zh-CN&cites=16308862699119587120", "cites_id": ["16308862699119587120"]}, "BBwRN1wAAAAJ:9yKSN-GCB0IC": {"container_type": "Publication", "source": "AUTHOR_PUBLICATION_ENTRY", "bib": {"title": "Automated surface damage detection and quantification in concrete structures using semantic point clouds", "pub_year": "2025"}, "filled": false, "author_pub_id": "BBwRN1wAAAAJ:9yKSN-GCB0IC", "num_citations": 3, "citedby_url": "https://scholar.google.com/scholar?oi=bibs&hl=zh-CN&cites=7393088708757161554", "cites_id": ["7393088708757161554"]}, "BBwRN1wAAAAJ:d1gkVwhDpl0C": {"container_type": "Publication", "source": "AUTHOR_PUBLICATION_ENTRY", "bib": {"title": "基于随机有限元法的非机动车钢桥摩擦型高强螺栓可靠性分析", "pub_year": "2022"}, "filled": false, "author_pub_id": "BBwRN1wAAAAJ:d1gkVwhDpl0C", "num_citations": 2, "citedby_url": "https://scholar.google.com/scholar?oi=bibs&hl=zh-CN&cites=425248390803648087", "cites_id": ["425248390803648087"]}, "BBwRN1wAAAAJ:u5HHmVD_uO8C": {"container_type": "Publication", "source": "AUTHOR_PUBLICATION_ENTRY", "bib": {"title": "Numerical Study on Optimal Geometric Parameters for Multi-performance of Friction High-Strength Bolts", "pub_year": "2022"}, "filled": false, "author_pub_id": "BBwRN1wAAAAJ:u5HHmVD_uO8C", "num_citations": 2, "citedby_url": "https://scholar.google.com/scholar?oi=bibs&hl=zh-CN&cites=5093901263718765697", "cites_id": ["5093901263718765697"]}, "BBwRN1wAAAAJ:qjMakFHDy7sC": {"container_type": "Publication", "source": "AUTHOR_PUBLICATION_ENTRY", "bib": {"title": "Reliability of friction highstrength bolts for non-motor vehicle steel bridges based on stochastic finite element analysis", "pub_year": "2022"}, "filled": false, "author_pub_id": "BBwRN1wAAAAJ:qjMakFHDy7sC", "num_citations": 2, "citedby_url": "https://scholar.google.com/scholar?oi=bibs&hl=zh-CN&cites=12523574725418099532", "cites_id": ["12523574725418099532"]}, "BBwRN1wAAAAJ:UeHWp8X0CEIC": {"container_type": "Publication", "source": "AUTHOR_PUBLICATION_ENTRY", "bib": {"title": "Bridge surface damage detection with structural context via boundary-aware component segmentation", "pub_year": "2026"}, "filled": false, "author_pub_id": "BBwRN1wAAAAJ:UeHWp8X0CEIC", "num_citations": 0}}, "citedby5y": 63, "hindex": 2, "hindex5y": 2, "i10index": 1, "i10index5y": 1, "cites_per_year": {"2023": 3, "2024": 3, "2025": 39, "2026": 18}, "updated": "2026-05-04 10:09:40.077278"}